kdtest/__init__.py
kdtest/common.py
kdtest/product.py
kdtest/reference.py
kdtest/run.py
kdtest/Interface/__init__.py
kdtest/Interface/common_Interface_Class.py
kdtest/action/__init__.py
kdtest/action/key_Retrieval.py
kdtest/action/page_Action.py
kdtest/cases/__init__.py
kdtest/cases/case_execution.py
kdtest/cases/read/__init__.py
kdtest/cases/read/cell_Value_Handle.py
kdtest/cases/read/excel_Read.py
kdtest/cases/read/run_Sheet_Row.py
kdtest/data/__init__.py
kdtest/data/init_data.py
kdtest/data/cache/cookie.txt
kdtest/data/cache/response_result.txt
kdtest/data/static/testCases.xlsx
kdtest/plugins/OA_webUI/OA_webUI.py
kdtest/plugins/OA_webUI/__init__.py
kdtest/plugins/OA_webUI/my.ini
kdtest/plugins/OA_webUI/elementData/elementData.yaml
kdtest/plugins/OA_webUI/elementData/modularInformation.json
kdtest/plugins/OA_webUI/utils/__init__.py
kdtest/plugins/OA_webUI/utils/tool.py
kdtest/utils/__init__.py
kdtest/utils/built_In_Function.py
kdtest/utils/decorator.py
kdtest/utils/environment_Configuration.py
kdtest/utils/public_Script.py
kdtest/utils/log/log.css
kdtest/utils/log/log.js
kdtest/utils/log/log.py
kdtest/utils/log/trusteeship.py
kdtest-1.1.6.dist-info/LICENSE.md
kdtest-1.1.6.dist-info/METADATA
kdtest-1.1.6.dist-info/WHEEL
kdtest-1.1.6.dist-info/entry_points.txt
kdtest-1.1.6.dist-info/top_level.txt
kdtest-1.1.6.dist-info/RECORD
