Metadata-Version: 2.1
Name: kdtest
Version: 1.1.6
Summary: A keyword-driven automated testing framework
Home-page: https://gitee.com/wang_qiao123/kdtest.git
Author: Qiao Wang
Author-email: 1603938216@qq.com
License: MIT License
Keywords: kdtest selenium request
Classifier: Programming Language :: Python :: 3
Classifier: License :: OSI Approved :: Apache Software License
Classifier: Operating System :: OS Independent
License-File: LICENSE.md
Requires-Dist: colorama (==0.4.4)
Requires-Dist: dominate (==2.6.0)
Requires-Dist: pipreqs (==0.4.11)
Requires-Dist: selenium (==3.141.0)
Requires-Dist: msedge-selenium-tools (==3.141.4)
Requires-Dist: requests (==2.27.1)
Requires-Dist: Eel (==0.15.2)
Requires-Dist: openpyxl (>=3.0.7)
Requires-Dist: pywinauto (>=0.6.8)
Requires-Dist: ruamel.yaml (>=0.17.21)
Requires-Dist: tqdm (>=4.63.0)
